AUTHORS
ChangeLog
LICENSE
Makefile
README.rst
requirements.txt
setup.cfg
setup.py
test-requirements.txt
tox.ini
purpler/__init__.py
purpler/base62.py
purpler/bot.py
purpler/store.py
purpler/wsgi.py
purpler.egg-info/PKG-INFO
purpler.egg-info/SOURCES.txt
purpler.egg-info/dependency_links.txt
purpler.egg-info/entry_points.txt
purpler.egg-info/not-zip-safe
purpler.egg-info/pbr.json
purpler.egg-info/requires.txt
purpler.egg-info/top_level.txt
purpler/templates/base.html
purpler/templates/irc.html
purpler/templates/logs.html
purpler/templates/style.css
purpler/tests/__init__.py
purpler/tests/test_storage.py
purpler/tests/test_uuid_base62.py