Metadata-Version: 1.1
Name: purpler
Version: 0.1.0
Summary: A suite of tools for purpling things
Home-page: https://github.com/cdent/purpler
Author: Chris Dent
Author-email: cdent@anticdent.org
License: Apache-2
Platform: UNKNOWN
Classifier: Intended Audience :: Developers
Classifier: Intended Audience :: Information Technology
Classifier: Environment :: Web Environment
Classifier: License :: OSI Approved :: Apache Software License
Classifier: Operating System :: POSIX
Classifier: Programming Language :: Python
Classifier: Programming Language :: Python :: 2
Classifier: Programming Language :: Python :: 2.7
Classifier: Programming Language :: Python :: 3
Classifier: Programming Language :: Python :: 3.4
Classifier: Programming Language :: Python :: 3.5
